AUTHORS.rst
CONTRIBUTING.rst
DESCRIPTION.rst
HISTORY.rst
INSTALLATION.rst
LICENSE
MANIFEST.in
README.rst
USAGE.rst
setup.py
supervisor_serialrestart.egg-info/PKG-INFO
supervisor_serialrestart.egg-info/SOURCES.txt
supervisor_serialrestart.egg-info/dependency_links.txt
supervisor_serialrestart.egg-info/not-zip-safe
supervisor_serialrestart.egg-info/top_level.txt
supervisorserialrestart/__init__.py
supervisorserialrestart/controllerplugin.py