Metadata-Version: 1.1
Name: supervisor-serialrestart
Version: 0.1.1
Summary: Adds serialrestart command to Supervisor.
Home-page: https://github.com/native2k/supervisorserialrestart
Author: Sven Richter
Author-email: native2k@gmail.com
License: BSD
Keywords: supervisorserialrestart supervisor-serialrestart supervisor serialrestart
Platform: UNKNOWN
Classifier: Development Status :: 2 - Pre-Alpha
Classifier: Intended Audience :: Developers
Classifier: License :: OSI Approved :: BSD License
Classifier: Natural Language :: English
Classifier: Programming Language :: Python :: 2
Classifier: Programming Language :: Python :: 2.6
Classifier: Programming Language :: Python :: 2.7
Classifier: Programming Language :: Python :: 3
Classifier: Programming Language :: Python :: 3.3
